Supplier_API_mock_server-2.0.5.data/data/README.md/README.md
Supplier_API_mock_server-2.0.5.data/data/requirements.txt/requirements.txt
supplier_server/__init__.py
supplier_server/app.py
supplier_server/auth.py
supplier_server/constants.py
supplier_server/error_handlers.py
supplier_server/exceptions.py
supplier_server/responses.py
supplier_server/utils.py
supplier_server/validation.py
Supplier_API_mock_server-2.0.5.dist-info/METADATA
Supplier_API_mock_server-2.0.5.dist-info/WHEEL
Supplier_API_mock_server-2.0.5.dist-info/entry_points.txt
Supplier_API_mock_server-2.0.5.dist-info/top_level.txt
Supplier_API_mock_server-2.0.5.dist-info/RECORD
