Metadata-Version: 2.1
Name: Supplier-API-mock-server
Version: 2.0.5
Summary: Mock Server with Supplier API implementation
Author: Tiqets Team
Author-email: connections@tiqets.com
Classifier: Programming Language :: Python
Classifier: Programming Language :: Python :: 3
Classifier: Programming Language :: Python :: 3.7
Classifier: License :: OSI Approved :: MIT License
Classifier: Operating System :: OS Independent
Requires-Python: >=3.7
Requires-Dist: arrow ==0.15.1
Requires-Dist: Flask ==2.2.5
Requires-Dist: uWSGI ==2.0.22
